materialsearch_core/__init__.py
materialsearch_core/config.py
materialsearch_core/database.py
materialsearch_core/models.py
materialsearch_core/process_assets.py
materialsearch_core/scan.py
materialsearch_core/search.py
materialsearch_core/utils.py
materialsearch_core-0.2.2.dist-info/METADATA
materialsearch_core-0.2.2.dist-info/WHEEL
materialsearch_core-0.2.2.dist-info/licenses/LICENSE
materialsearch_core-0.2.2.dist-info/RECORD
